<?xml version="1.0" encoding="utf-8" ?>
<jobs>
	<job>
		<dates>
		Май 2012 — декабрь 2012
		</dates>
		<titles>
		ЭкоСофт (Иркутск)
		</titles>
		<post>
		Программист, по совместительству верстальщик
		</post>
		<resps>
			<resp>Разработка сайтов</resp>
			<resp>Верстка макетов</resp>
			<resp>Разработка компонентов, модулей для CMS Joomla</resp>
			<resp>Доработка и поддержка сайтов компании</resp>
		</resps>
	</job>
	<job>
		<dates>
		Март 2009 — май 2011
		</dates>
		<titles>
		Фриланс
		</titles>
		<post>
		Программист, по совместительству верстальщик
		</post>
		<resps>
			<resp>Разработка сайтов</resp>
			<resp>Верстка макетов</resp>
			<resp>Модификация компонентов\модулей\плагинов для различных CMS</resp>
			<resp>Наполнение</resp>
		</resps>
	</job>
	<job>
		<dates>
		Ноябрь 2008 — март 2009
		</dates>
		<titles>
		Инсайт (Иркутск)
		</titles>
		<post>
		Программист, по совместительству верстальщик
		</post>
		<resps>
			<resp>Разработка сайтов</resp>
			<resp>Верстка макетов</resp>
			<resp>Разработка компонентов, модулей для CMS</resp>
			<resp>Доработка и поддержка сайтов компании</resp>
		</resps>
	</job>
</jobs>